alice_pdf/__init__.py
alice_pdf/camelot_extractor.py
alice_pdf/cli.py
alice_pdf/extractor.py
alice_pdf/pdfplumber_extractor.py
alice_pdf/prompt_generator.py
alice_pdf/textract_extractor.py
alice_pdf-0.1.3.dist-info/METADATA
alice_pdf-0.1.3.dist-info/WHEEL
alice_pdf-0.1.3.dist-info/entry_points.txt
alice_pdf-0.1.3.dist-info/licenses/LICENSE
alice_pdf-0.1.3.dist-info/RECORD
