Metadata-Version: 2.4
Name: alice-pdf
Version: 0.1.3
Summary: Extract tables from PDFs using Mistral OCR
Project-URL: Homepage, https://github.com/aborruso/alice-pdf
Project-URL: Issues, https://github.com/aborruso/alice-pdf/issues
Author-email: Andrea Borruso <aborruso@gmail.com>
License: MIT
License-File: LICENSE
Keywords: csv,mistral,ocr,pdf,table-extraction
Classifier: Development Status :: 3 - Alpha
Classifier: Intended Audience :: Developers
Classifier: License :: OSI Approved :: MIT License
Classifier: Programming Language :: Python :: 3
Classifier: Programming Language :: Python :: 3.9
Classifier: Programming Language :: Python :: 3.10
Classifier: Programming Language :: Python :: 3.11
Classifier: Programming Language :: Python :: 3.12
Requires-Python: >=3.9
Requires-Dist: boto3>=1.26.0
Requires-Dist: camelot-py>=1.0.9
Requires-Dist: mistralai>=1.0.0
Requires-Dist: pandas>=2.0.0
Requires-Dist: pdfplumber>=0.11.0
Requires-Dist: pillow>=10.0.0
Requires-Dist: pymupdf>=1.23.0
Requires-Dist: pyyaml>=6.0.0
Provides-Extra: dev
Requires-Dist: pytest-cov>=4.0.0; extra == 'dev'
Requires-Dist: pytest-mock>=3.10.0; extra == 'dev'
Requires-Dist: pytest>=7.0.0; extra == 'dev'
